odoo8_addon_stock_picking_invoice_link-8.0.2.1.2-py3.8-nspkg.pth
odoo_addons/stock_picking_invoice_link/README.rst
odoo_addons/stock_picking_invoice_link/__init__.py
odoo_addons/stock_picking_invoice_link/__openerp__.py
odoo_addons/stock_picking_invoice_link/i18n/ar.po
odoo_addons/stock_picking_invoice_link/i18n/bg.po
odoo_addons/stock_picking_invoice_link/i18n/bs.po
odoo_addons/stock_picking_invoice_link/i18n/ca.po
odoo_addons/stock_picking_invoice_link/i18n/cs.po
odoo_addons/stock_picking_invoice_link/i18n/de.po
odoo_addons/stock_picking_invoice_link/i18n/el_GR.po
odoo_addons/stock_picking_invoice_link/i18n/en_GB.po
odoo_addons/stock_picking_invoice_link/i18n/es.po
odoo_addons/stock_picking_invoice_link/i18n/es_AR.po
odoo_addons/stock_picking_invoice_link/i18n/es_CR.po
odoo_addons/stock_picking_invoice_link/i18n/es_EC.po
odoo_addons/stock_picking_invoice_link/i18n/es_MX.po
odoo_addons/stock_picking_invoice_link/i18n/es_PE.po
odoo_addons/stock_picking_invoice_link/i18n/et.po
odoo_addons/stock_picking_invoice_link/i18n/fi.po
odoo_addons/stock_picking_invoice_link/i18n/fr.po
odoo_addons/stock_picking_invoice_link/i18n/fr_CA.po
odoo_addons/stock_picking_invoice_link/i18n/fr_CH.po
odoo_addons/stock_picking_invoice_link/i18n/gl.po
odoo_addons/stock_picking_invoice_link/i18n/hr.po
odoo_addons/stock_picking_invoice_link/i18n/hr_HR.po
odoo_addons/stock_picking_invoice_link/i18n/hu.po
odoo_addons/stock_picking_invoice_link/i18n/id.po
odoo_addons/stock_picking_invoice_link/i18n/it.po
odoo_addons/stock_picking_invoice_link/i18n/ja.po
odoo_addons/stock_picking_invoice_link/i18n/lt.po
odoo_addons/stock_picking_invoice_link/i18n/mk.po
odoo_addons/stock_picking_invoice_link/i18n/mn.po
odoo_addons/stock_picking_invoice_link/i18n/nb.po
odoo_addons/stock_picking_invoice_link/i18n/nb_NO.po
odoo_addons/stock_picking_invoice_link/i18n/nl.po
odoo_addons/stock_picking_invoice_link/i18n/nl_BE.po
odoo_addons/stock_picking_invoice_link/i18n/nl_NL.po
odoo8_addon_stock_picking_invoice_link-8.0.2.1.2.dist-info/METADATA
odoo8_addon_stock_picking_invoice_link-8.0.2.1.2.dist-info/WHEEL
odoo8_addon_stock_picking_invoice_link-8.0.2.1.2.dist-info/namespace_packages.txt
odoo8_addon_stock_picking_invoice_link-8.0.2.1.2.dist-info/top_level.txt
odoo8_addon_stock_picking_invoice_link-8.0.2.1.2.dist-info/RECORD
