Metadata-Version: 2.1
Name: odoo8-addon-stock-picking-invoice-link
Version: 8.0.2.1.2
Summary: Adds link between pickings and generated invoices
Home-page: http://www.agilebg.com
Author: Agile Business Group, Tecnativa, Odoo Community Association (OCA)
Author-email: support@odoo-community.org
License: AGPL-3
Platform: UNKNOWN
Classifier: Programming Language :: Python
Classifier: Framework :: Odoo
Classifier: License :: OSI Approved :: GNU Affero General Public License v3
Requires-Python: ~=2.7
Requires-Dist: odoo (<9.0a,>=8.0a)
